data_exporer/__init__.py
data_exporer/getter.py
worldbank_sn-0.1.0.dist-info/METADATA
worldbank_sn-0.1.0.dist-info/WHEEL
worldbank_sn-0.1.0.dist-info/top_level.txt
worldbank_sn-0.1.0.dist-info/RECORD
