Metadata-Version: 2.4
Name: worldbank-sn
Version: 0.1.0
Summary: Package Python pour récupérer les données économiques du Sénégal via l'API World Bank
Author-email: attoisse <attoissemohamed@gmail.com>
License: MIT
Requires-Python: >=3.7
Requires-Dist: pandas
